dataCAT/__init__.py
dataCAT/__version__.py
dataCAT/_parse_settings.py
dataCAT/context_managers.py
dataCAT/create_database.py
dataCAT/database.py
dataCAT/df_proxy.py
dataCAT/df_proxy.pyi
dataCAT/dtype.py
dataCAT/functions.py
dataCAT/hdf5_log.py
dataCAT/pdb_array.py
dataCAT/property_dset.py
dataCAT/py.typed
dataCAT/testing_utils.py
dataCAT/data/CCCCCCCCN[CCCCCCCC]CCCCCCCC@N9.pdb
dataCAT/data/CCCCCCCCP[CCCCCCCC]CCCCCCCC@P9.pdb
dataCAT/data/CCCCCCC[=O]O@C6.pdb
dataCAT/data/CCCCCCC[=O][O-]@O8.pdb
dataCAT/data/CCCCCCC[=O][O-]@O9.pdb
dataCAT/data/CCCC[O-]@O5.pdb
dataCAT/data/CCCNCCC[=O]O@C5.pdb
dataCAT/data/CCCNCCC[=O][O-]@O8.pdb
dataCAT/data/CCCNCCC[=O][O-]@O9.pdb
dataCAT/data/CCCOCCC[=O]O@C5.pdb
dataCAT/data/CCCOCCC[=O][O-]@O8.pdb
dataCAT/data/CCCOCCC[=O][O-]@O9.pdb
dataCAT/data/CCC[=O][O-]@O5.pdb
dataCAT/data/CCO@O3.pdb
dataCAT/data/CC[=O][O-]@O4.pdb
dataCAT/data/CC[O-]@O3.pdb
dataCAT/data/CN@N2.pdb
dataCAT/data/CNC[=O][O-]@O5.pdb
dataCAT/data/CO@O2.pdb
dataCAT/data/COC[=O][O-]@O5.pdb
dataCAT/data/C[NH-]@N2.pdb
dataCAT/data/C[O-]@O2.pdb
dataCAT/data/O=C[O-]@O3.pdb
dataCAT/data/__init__.py
Data_CAT-0.7.2.dist-info/LICENSE.md
Data_CAT-0.7.2.dist-info/METADATA
Data_CAT-0.7.2.dist-info/WHEEL
Data_CAT-0.7.2.dist-info/top_level.txt
Data_CAT-0.7.2.dist-info/RECORD
