Metadata-Version: 2.1
Name: Data-CAT
Version: 0.7.2
Summary: A databasing framework for the Compound Attachment Tools package (CAT).
Home-page: https://github.com/nlesc-nano/data-CAT
Author: ['B. F. van Beek']
Author-email: b.f.van.beek@vu.nl
License: GNU Lesser General Public License v3 or later
Keywords: database,science,chemistry,python-3,python-3-7,python-3-8,python-3-9,python-3-10,automation
Platform: UNKNOWN
Classifier: Development Status :: 3 - Alpha
Classifier: Intended Audience :: Science/Research
Classifier: License :: OSI Approved :: GNU General Public License v3 or later (GPLv3+)
Classifier: Natural Language :: English
Classifier: Operating System :: Unix
Classifier: Operating System :: MacOS
Classifier: Programming Language :: Python :: 3.7
Classifier: Programming Language :: Python :: 3.8
Classifier: Programming Language :: Python :: 3.9
Classifier: Programming Language :: Python :: 3.10
Classifier: Topic :: Database
Classifier: Typing :: Typed
Requires-Python: >=3.7
License-File: LICENSE.md
Requires-Dist: h5py (>=3.0.0)
Requires-Dist: numpy
Requires-Dist: pandas
Requires-Dist: pymongo
Requires-Dist: Nano-Utils (>=0.4.3)
Requires-Dist: AssertionLib (>=2.2.0)
Requires-Dist: plams (>=1.5.1)
Requires-Dist: nlesc-CAT (>=0.10.0)
Provides-Extra: build
Requires-Dist: twine ; extra == 'build'
Requires-Dist: wheel ; extra == 'build'
Provides-Extra: test
Requires-Dist: pytest (>=5.4.0) ; extra == 'test'
Requires-Dist: pytest-cov ; extra == 'test'
Requires-Dist: nlesc-CAT (>=0.10.1) ; extra == 'test'
Requires-Dist: twine ; extra == 'test'
Requires-Dist: wheel ; extra == 'test'
